neelanjanmannac.py
neelanjanmannac-5.dist-info/METADATA
neelanjanmannac-5.dist-info/WHEEL
neelanjanmannac-5.dist-info/top_level.txt
neelanjanmannac-5.dist-info/RECORD
